group_lasso/__init__.py
group_lasso/_fista.py
group_lasso/_group_lasso.py
group_lasso/_singular_values.py
group_lasso/_subsampling.py
group_lasso/utils.py
group_lasso/__pycache__/__init__.cpython-38.pyc
group_lasso/__pycache__/_fista.cpython-38.pyc
group_lasso/__pycache__/_group_lasso.cpython-38.pyc
group_lasso/__pycache__/_singular_values.cpython-38.pyc
group_lasso/__pycache__/_subsampling.cpython-38.pyc
group_lasso/__pycache__/utils.cpython-38.pyc
group_lasso-1.5.0.dist-info/LICENSE
group_lasso-1.5.0.dist-info/METADATA
group_lasso-1.5.0.dist-info/WHEEL
group_lasso-1.5.0.dist-info/top_level.txt
group_lasso-1.5.0.dist-info/RECORD
