Metadata-Version: 2.1
Name: group-lasso
Version: 1.5.0
Summary: Fast group lasso regularised linear models in a sklearn-style API.
Home-page: UNKNOWN
Author: Yngve Mardal Moe
Author-email: yngve.m.moe@gmail.com
License: MIT
Platform: UNKNOWN
Requires-Dist: numpy
Requires-Dist: scikit-learn
